state_space/__init__.py
state_space/compiled_matrix.py
state_space/data_reader.py
state_space/linearize_vector_valued_state_function.py
state_space/parameter_transformation.py
state_space/symbolic_dimension_checks.py
state_space/symbolic_state_space_model.py
state_space/examples/__init__.py
state_space/examples/conditional_univariate_linear_factor_model.py
state_space/examples/symbolic_time_varying_equity_premium_model.py
state_space/tests/__init__.py
state_space-0.0.3.dist-info/LICENSE
state_space-0.0.3.dist-info/METADATA
state_space-0.0.3.dist-info/WHEEL
state_space-0.0.3.dist-info/top_level.txt
state_space-0.0.3.dist-info/RECORD
