Metadata-Version: 2.1
Name: state-space
Version: 0.0.3
Summary: State Space Models in Python
Home-page: https://github.com/michaelnowotny/state_space.git
Author: Michael Christoph Nowotny
Author-email: nowotnym@gmail.com
License: MIT
Platform: UNKNOWN
Classifier: License :: OSI Approved :: MIT License
Classifier: Programming Language :: Python
Classifier: Programming Language :: Python :: 3
Classifier: Programming Language :: Python :: 3.7
Classifier: Programming Language :: Python :: 3.8
Classifier: Programming Language :: Python :: 3.9
Classifier: Programming Language :: Python :: Implementation :: CPython
Requires-Python: >=3.6.0
Requires-Dist: numpy
Requires-Dist: statsmodels
Requires-Dist: sympy
Requires-Dist: pytest
